{"cameraMode":{"drawMode":0,"name":"Shaded","section":"Shading Mode"},"sceneLighting":false,"audioPlay":false,"sceneViewState":{"m_AlwaysRefresh":false,"showFog":true,"showSkybox":false,"showFlares":true,"showImageEffects":true,"showParticleSystems":true,"showVisualEffectGraphs":true,"m_FxEnabled":true},"in2DMode":false,"pivot":{"x":20.10536003112793,"y":19.935483932495118,"z":22.249126434326173},"rotation":{"x":-0.2430141717195511,"y":-0.4769044518470764,"z":0.13908766210079194,"w":-0.8331099152565002},"size":7.527092933654785,"orthographic":false}